<?xml version="1.0"?>
<!DOCTYPE hibernate-mapping PUBLIC "-//Hibernate/Hibernate Mapping DTD 3.0//EN"
"http://www.hibernate.org/dtd/hibernate-mapping-3.0.dtd">
<!-- Generated 2017-8-23 17:10:04 by Hibernate Tools 4.3.1.Final -->
<hibernate-mapping>
    <class name="com.shjn.model.Cxdj" table="cxdj" catalog="amac" optimistic-lock="version">
        <id name="id" type="java.lang.Integer">
            <column name="id" />
            <generator class="identity" />
        </id>
        <property name="organization" type="string">
            <column name="organization" length="45" />
        </property>
        <property name="disciplinary" type="string">
            <column name="disciplinary" length="45" />
        </property>
        <property name="revocationDate" type="date">
            <column name="revocation_date" length="10" />
        </property>
        <property name="createTimestamp" type="timestamp">
            <column name="create_timestamp" length="19" />
        </property>
        <property name="updateTimestamp" type="timestamp">
            <column name="update_timestamp" length="19" />
        </property>
    </class>
</hibernate-mapping>
